{"2017-8":[{"title":"如何安装Hexo开始你的博客生涯","date":"2017-08-18T07:41:00.000Z","link":"/hello_world/"}],"2020-3":[{"title":"黑苹果 ｜ 详解Clove配置","date":"2020-03-30T14:43:00.000Z","link":"/黑苹果-｜-详解Clove配置/"},{"title":"黑苹果 ｜ 常见的驱动配置","date":"2020-03-30T15:58:00.000Z","link":"/黑苹果-｜-常见的驱动配置/"}],"2020-4":[{"title":"【黑果小兵】macOS Catalina 10.15.4 19E266 正式版 with Clover 5107原版镜像[双EFI版][UEFI and MBR]","date":"2020-04-03T16:56:00.000Z","link":"/【黑果小兵】macOS-Catalina-10-15-4-19E266-正式版-with-Clover-5107原版镜像-双EFI版-UEFI-and-MBR/"},{"title":"使用AppleALC声卡仿冒驱动AppleHDA的正确姿势","date":"2020-04-03T16:58:00.000Z","link":"/使用AppleALC声卡仿冒驱动AppleHDA的正确姿势/"},{"title":"DW1820A/BCM94350ZAE/BCM94356ZEPA50DX插入的正确姿势","date":"2020-04-03T17:00:00.000Z","link":"/DW1820A-BCM94350ZAE-BCM94356ZEPA50DX插入的正确姿势/"},{"title":"给你的博客增加B站追番页面","date":"2020-04-06T04:02:03.000Z","link":"/AddBlibli/"}]}